blog/__init__.py
blog/admin.py
blog/apps.py
blog/date_conversions.py
blog/forms.py
blog/markdown_parser.py
blog/models.py
blog/tests.py
blog/urls.py
blog/views.py
blog/migrations/0001_initial.py
blog/migrations/0002_auto_20200113_0338.py
blog/migrations/0003_auto_20200127_1045.py
blog/migrations/__init__.py
lukepafford_blog/__init__.py
lukepafford_blog/asgi.py
lukepafford_blog/settings.py
lukepafford_blog/urls.py
lukepafford_blog/wsgi.py
public/__init__.py
public/dist/css/base.css
public/dist/css/code_highlight.css
public/dist/js/bundle.js
templates/__init__.py
templates/_base.html
templates/__pycache__/__init__.cpython-37.pyc
templates/blog/post_upload.html
templates/blog/posts_detail.html
templates/blog/posts_list.html
user/__init__.py
user/admin.py
user/apps.py
user/models.py
user/tests.py
user/views.py
user/migrations/0001_initial.py
user/migrations/__init__.py
django_lukepafford_blog-1.0.27.dist-info/METADATA
django_lukepafford_blog-1.0.27.dist-info/WHEEL
django_lukepafford_blog-1.0.27.dist-info/entry_points.txt
django_lukepafford_blog-1.0.27.dist-info/top_level.txt
django_lukepafford_blog-1.0.27.dist-info/RECORD
